catflow_worker/__init__.py
catflow_worker/__main__.py
catflow_worker/_version.py
catflow_worker/main.py
catflow_worker/types.py
catflow_worker/worker.py
catflow_worker-0.1.8.dist-info/LICENSE
catflow_worker-0.1.8.dist-info/METADATA
catflow_worker-0.1.8.dist-info/WHEEL
catflow_worker-0.1.8.dist-info/top_level.txt
catflow_worker-0.1.8.dist-info/RECORD
