Metadata-Version: 2.1
Name: catflow-worker
Version: 0.1.8
Summary: Consumer/publisher loop for workers in an object recognition pipeline
Author-email: Ian Kilgore <iank@iank.org>
License: MIT License
Requires-Python: >=3.7
License-File: LICENSE
Requires-Dist: aio-pika (>=9.1.3)
Requires-Dist: aioboto3 (>=11.2.0)
Requires-Dist: aiobotocore (>=2.5.0)
Requires-Dist: boto3 (>=1.26.76)
Requires-Dist: botocore (>=1.29.76)
Requires-Dist: marshmallow (>=3.19.0)
Provides-Extra: dev
Requires-Dist: pytest ; extra == 'dev'
Requires-Dist: pytest-asyncio ; extra == 'dev'
Requires-Dist: pytest-rabbitmq ; extra == 'dev'
Requires-Dist: moto[server] (>=4.1.11) ; extra == 'dev'
Requires-Dist: aiofile ; extra == 'dev'
